control/__init__.py
control/_version.py
control/bdalg.py
control/canonical.py
control/config.py
control/ctrlplot.py
control/ctrlutil.py
control/delay.py
control/descfcn.py
control/dtime.py
control/exception.py
control/frdata.py
control/freqplot.py
control/grid.py
control/iosys.py
control/lti.py
control/margins.py
control/mateqn.py
control/modelsimp.py
control/nichols.py
control/nlsys.py
control/optimal.py
control/passivity.py
control/phaseplot.py
control/pzmap.py
control/rlocus.py
control/robust.py
control/sisotool.py
control/statefbk.py
control/statesp.py
control/stochsys.py
control/sysnorm.py
control/timeplot.py
control/timeresp.py
control/xferfcn.py
control/bench/time_freqresp.py
control/flatsys/__init__.py
control/flatsys/basis.py
control/flatsys/bezier.py
control/flatsys/bspline.py
control/flatsys/flatsys.py
control/flatsys/linflat.py
control/flatsys/poly.py
control/flatsys/systraj.py
control/matlab/__init__.py
control/matlab/timeresp.py
control/matlab/wrappers.py
control/tests/__init__.py
control/tests/bdalg_test.py
control/tests/bspline_test.py
control/tests/canonical_test.py
control/tests/config_test.py
control/tests/conftest.py
control/tests/convert_test.py
control/tests/ctrlplot_test.py
control/tests/ctrlutil_test.py
control/tests/delay_test.py
control/tests/descfcn_test.py
control/tests/discrete_test.py
control/tests/docstrings_test.py
control/tests/flatsys_test.py
control/tests/frd_test.py
control/tests/freqplot_test.py
control/tests/freqresp_test.py
control/tests/input_element_int_test.py
control/tests/interconnect_test.py
control/tests/iosys_test.py
control/tests/kwargs_test.py
control/tests/lti_test.py
control/tests/margin_test.py
control/tests/mateqn_test.py
control/tests/matlab2_test.py
control/tests/matlab_test.py
control/tests/minreal_test.py
control/tests/modelsimp_test.py
control/tests/namedio_test.py
control/tests/nichols_test.py
control/tests/nlsys_test.py
control/tests/nyquist_test.py
control/tests/optimal_test.py
control-0.10.1.dist-info/LICENSE
control-0.10.1.dist-info/METADATA
control-0.10.1.dist-info/WHEEL
control-0.10.1.dist-info/top_level.txt
control-0.10.1.dist-info/RECORD
