Metadata-Version: 2.1
Name: control
Version: 0.10.1
Summary: Python Control Systems Library
Author-email: Python Control Developers <python-control-developers@lists.sourceforge.net>
License: BSD-3-Clause
Project-URL: homepage, https://python-control.org
Project-URL: source, https://github.com/python-control/python-control
Classifier: Development Status :: 4 - Beta
Classifier: Intended Audience :: Science/Research
Classifier: Intended Audience :: Developers
Classifier: License :: OSI Approved :: BSD License
Classifier: Programming Language :: Python :: 3
Classifier: Programming Language :: Python :: 3.10
Classifier: Programming Language :: Python :: 3.11
Classifier: Programming Language :: Python :: 3.12
Classifier: Topic :: Software Development
Classifier: Topic :: Scientific/Engineering
Classifier: Operating System :: Microsoft :: Windows
Classifier: Operating System :: POSIX
Classifier: Operating System :: Unix
Classifier: Operating System :: MacOS
Requires-Python: >=3.10
License-File: LICENSE
Requires-Dist: numpy>=1.23
Requires-Dist: scipy>=1.8
Requires-Dist: matplotlib>=3.6
Provides-Extra: test
Requires-Dist: pytest; extra == "test"
Requires-Dist: pytest-timeout; extra == "test"
Requires-Dist: ruff; extra == "test"
Provides-Extra: slycot
Requires-Dist: slycot>=0.4.0; extra == "slycot"
Provides-Extra: cvxopt
Requires-Dist: cvxopt>=1.2.0; extra == "cvxopt"
